sollol/__init__.py
sollol/adapters.py
sollol/adaptive_metrics.py
sollol/adaptive_parallelism.py
sollol/aggregation.py
sollol/auth.py
sollol/autobatch.py
sollol/batch.py
sollol/batch_manager.py
sollol/circuit_breaker.py
sollol/cli.py
sollol/client.py
sollol/cluster.py
sollol/config.py
sollol/coordinator_manager.py
sollol/dashboard.py
sollol/dashboard_client.py
sollol/dashboard_launcher.py
sollol/dashboard_log_hooks.py
sollol/dashboard_service.py
sollol/discovery.py
sollol/distributed_coordinator.py
sollol/distributed_pipeline.py
sollol/distributed_tracing.py
sollol/docker_ip_resolver.py
sollol/embedding_cache.py
sollol/execution.py
sollol/gateway.py
sollol/gpu_auto_setup.py
sollol/gpu_controller.py
sollol/gpu_redis_subscriber.py
sollol/graceful_shutdown.py
sollol/hedging.py
sollol/hedging_async.py
sollol/hybrid_router.py
sollol/install_systemd_service.py
sollol/integration.py
sollol/intelligence.py
sollol/intelligent_gpu_router.py
sollol/llama_cpp_coordinator.py
sollol/llama_cpp_rpc.py
sollol/memory.py
sollol/metrics.py
sollol/metrics_logger.py
sollol/model_sizes.py
sollol/network_observer.py
sollol/node_cluster.py
sollol/node_health.py
sollol/ollama_gguf_resolver.py
sollol/ollama_node.py
sollol/pool.py
sollol/prioritization.py
sollol/priority_helpers.py
sollol/rate_limiter.py
sollol/ray_advanced_router.py
sollol/ray_hybrid_router.py
sollol/registry.py
sollol/request_timeout.py
sollol/response_cache.py
sollol/retry_logic.py
sollol/routing_logger.py
sollol/routing_modes.py
sollol/routing_strategy.py
sollol/routing_viewer.py
sollol/rpc_auto_setup.py
sollol/rpc_discovery.py
sollol/rpc_registry.py
sollol/serve.py
sollol/setup_llama_cpp.py
sollol/sollol.py
sollol/sync_wrapper.py
sollol/tasks.py
sollol/unified_dashboard.py
sollol/vram_monitor.py
sollol/workers.py
sollol-0.9.66.dist-info/licenses/LICENSE
sollol-0.9.66.dist-info/METADATA
sollol-0.9.66.dist-info/WHEEL
sollol-0.9.66.dist-info/entry_points.txt
sollol-0.9.66.dist-info/top_level.txt
sollol-0.9.66.dist-info/RECORD
