Metadata-Version: 2.4
Name: sollol
Version: 0.9.66
Summary: Intelligent Load Balancer for Ollama Clusters - Adaptive Parallelism + VRAM-Aware GPU Routing + Ray/Dask/llama.cpp Distribution
Home-page: https://github.com/BenevolentJoker-JohnL/SOLLOL
Author: BenevolentJoker-JohnL
Author-email: BenevolentJoker-JohnL <benevolentjoker@gmail.com>
License: MIT
Project-URL: Homepage, https://github.com/BenevolentJoker-JohnL/SOLLOL
Project-URL: Documentation, https://github.com/BenevolentJoker-JohnL/SOLLOL/blob/main/README.md
Project-URL: Repository, https://github.com/BenevolentJoker-JohnL/SOLLOL
Project-URL: Bug Tracker, https://github.com/BenevolentJoker-JohnL/SOLLOL/issues
Keywords: ai,llm,distributed,ollama,load-balancing,inference,llama-cpp
Classifier: Development Status :: 4 - Beta
Classifier: Intended Audience :: Developers
Classifier: Intended Audience :: Science/Research
Classifier: Topic :: Scientific/Engineering :: Artificial Intelligence
Classifier: Topic :: System :: Distributed Computing
Classifier: License :: OSI Approved :: MIT License
Classifier: Programming Language :: Python :: 3
Classifier: Programming Language :: Python :: 3.8
Classifier: Programming Language :: Python :: 3.9
Classifier: Programming Language :: Python :: 3.10
Classifier: Programming Language :: Python :: 3.11
Requires-Python: >=3.8
License-File: LICENSE
Requires-Dist: requests>=2.31.0
Requires-Dist: httpx>=0.24.0
Requires-Dist: ipaddress>=1.0.23
Requires-Dist: ollama>=0.1.0
Requires-Dist: dask[distributed]>=2024.1.0
Requires-Dist: ray[default]>=2.0.0
Requires-Dist: prometheus-client>=0.12.0
Requires-Dist: rich>=13.7.0
Requires-Dist: typer>=0.19.0
Requires-Dist: flask>=2.0.0
Requires-Dist: flask-cors>=4.0.0
Requires-Dist: flask-sock>=0.7.0
Requires-Dist: gevent>=23.9.0
Requires-Dist: gevent-websocket>=0.10.1
Requires-Dist: fastapi>=0.104.0
Requires-Dist: uvicorn>=0.24.0
Requires-Dist: starlette>=0.27.0
Requires-Dist: redis>=5.0.0
Requires-Dist: bokeh>=3.1.0
Requires-Dist: gpustat>=1.0.0
Provides-Extra: dev
Requires-Dist: pytest>=7.0.0; extra == "dev"
Requires-Dist: pytest-asyncio>=1.2.0; extra == "dev"
Requires-Dist: pytest-cov>=4.0.0; extra == "dev"
Requires-Dist: flake8>=6.0.0; extra == "dev"
Requires-Dist: black>=23.0.0; extra == "dev"
Requires-Dist: isort>=5.0.0; extra == "dev"
Requires-Dist: mypy>=1.0.0; extra == "dev"
Provides-Extra: metrics
Requires-Dist: influxdb-client>=1.36.0; extra == "metrics"
Dynamic: author
Dynamic: home-page
Dynamic: license-file
Dynamic: requires-python
